kg_mcp/__init__.py
kg_mcp/__main__.py
kg_mcp/config.py
kg_mcp/main.py
kg_mcp/utils.py
kg_mcp/cli/__init__.py
kg_mcp/cli/setup.py
kg_mcp/cli/status.py
kg_mcp/codegraph/__init__.py
kg_mcp/codegraph/indexer.py
kg_mcp/codegraph/model.py
kg_mcp/kg/__init__.py
kg_mcp/kg/apply_schema.py
kg_mcp/kg/ingest.py
kg_mcp/kg/neo4j.py
kg_mcp/kg/repo.py
kg_mcp/kg/retrieval.py
kg_mcp/kg/schema.cypher
kg_mcp/llm/__init__.py
kg_mcp/llm/client.py
kg_mcp/llm/schemas.py
kg_mcp/llm/prompts/__init__.py
kg_mcp/llm/prompts/extractor.py
kg_mcp/llm/prompts/linker.py
kg_mcp/mcp/__init__.py
kg_mcp/mcp/change_schemas.py
kg_mcp/mcp/prompts.py
kg_mcp/mcp/resources.py
kg_mcp/mcp/tools.py
kg_mcp/security/__init__.py
kg_mcp/security/auth.py
kg_mcp/security/origin.py
kg_mcp-0.1.10.dist-info/METADATA
kg_mcp-0.1.10.dist-info/WHEEL
kg_mcp-0.1.10.dist-info/entry_points.txt
kg_mcp-0.1.10.dist-info/RECORD
